{
  "project_info": {
    "project_number": "1042655623131",
    "project_id": "mybiz-aae0e",
    "storage_bucket": "mybiz-aae0e.firebasestorage.app"
  },
  "client": [
    {
      "client_info": {
        "mobilesdk_app_id": "1:1042655623131:android:38bff255ce1122ebf719fe",
        "android_client_info": {
          "package_name": "com.example.mybiz"
        }
      },
      "oauth_client": [],
      "api_key": [
        {
          "current_key": "AIzaSyANVrIIKL--C6G5cmSFhsLi76J0YUY5Wps"
        }
      ],
      "services": {
        "appinvite_service": {
          "other_platform_oauth_client": []
        }
      }
    }
  ],
  "configuration_version": "1"
}